sklearn_jax_kernels/__init__.py
sklearn_jax_kernels/base_kernels.py
sklearn_jax_kernels/config.py
sklearn_jax_kernels/gpc.py
sklearn_jax_kernels/structured/string_utils.py
sklearn_jax_kernels/structured/strings.py
sklearn_jax_kernels-0.0.2.dist-info/WHEEL
sklearn_jax_kernels-0.0.2.dist-info/METADATA
sklearn_jax_kernels-0.0.2.dist-info/RECORD
