Metadata-Version: 2.1
Name: sklearn-jax-kernels
Version: 0.0.2
Summary: Composable kernels for scikit-learn implemented in JAX.
Home-page: https://github.com/ExpectationMax/sklearn-jax-kernels
Author: Max Horn
Author-email: max.horn@bsse.ethz.ch
Requires-Python: >=3.6,<4.0
Classifier: Programming Language :: Python :: 3
Classifier: Programming Language :: Python :: 3.6
Classifier: Programming Language :: Python :: 3.7
Classifier: Programming Language :: Python :: 3.8
Requires-Dist: jax (>=0.1.59,<0.2.0)
Requires-Dist: jaxlib (>=0.1.40,<0.2.0)
Requires-Dist: scikit-learn (>=0.23.0,<0.24.0)
Project-URL: Repository, https://github.com/ExpectationMax/sklearn-jax-kernels
